mgiou/__init__.py
mgiou/losses.py
mgiou-0.1.0.dist-info/METADATA
mgiou-0.1.0.dist-info/WHEEL
mgiou-0.1.0.dist-info/top_level.txt
mgiou-0.1.0.dist-info/RECORD
