Metadata-Version: 2.4
Name: MGIoU
Version: 0.1.0
Summary: Marginalised Generalised IoU (MGIoU) loss for PyTorch
Author-email: Duy-Tho Le <ldtho.97@gmail.com>
License: MIT
Project-URL: Homepage, https://github.com/ldtho/MGIoU
Classifier: Programming Language :: Python :: 3
Classifier: License :: OSI Approved :: MIT License
Classifier: Topic :: Scientific/Engineering :: Artificial Intelligence
Requires-Python: >=3.8
